client/__init__.py
client/client.py
crypto/__init__.py
crypto/crypto.py
methods/__init__.py
methods/methods.py
my_types/__init__.py
my_types/socket/__init__.py
my_types/socket/message.py
network/__init__.py
network/helper.py
network/network.py
network/socket.py
sessions/__init__.py
sessions/sessions.py
utils/__init__.py
utils/configs.py
utils/utils.py
rubka_webapi-3.7.9.dist-info/METADATA
rubka_webapi-3.7.9.dist-info/WHEEL
rubka_webapi-3.7.9.dist-info/top_level.txt
rubka_webapi-3.7.9.dist-info/RECORD
