Metadata-Version: 2.4
Name: rubka_webapi
Version: 3.7.9
Summary: یک کتابخانه قدرتمند و آسان برای ساخت ربات‌های خودکار در روبیکا.
Home-page: https://github.com/xetay12/rubka_webapi
Author: httex
Author-email: wanwsnys69@gmail.com
Keywords: rubika,rubino,pyrubi,pyrubika,bot,chat
Classifier: Programming Language :: Python :: 3.7
Classifier: Programming Language :: Python :: 3.8
Classifier: Programming Language :: Python :: 3.9
Classifier: Programming Language :: Python :: 3.10
Classifier: Programming Language :: Python :: 3.11
Classifier: Programming Language :: Python :: 3.12
Classifier: License :: OSI Approved :: GNU Lesser General Public License v3 (LGPLv3)
Classifier: Topic :: Internet
Classifier: Topic :: Communications
Classifier: Topic :: Communications :: Chat
Classifier: Topic :: Software Development :: Libraries
Classifier: Topic :: Software Development :: Libraries :: Python Modules
Classifier: Topic :: Software Development :: Libraries :: Application Frameworks
Requires-Python: ~=3.7
Requires-Dist: urllib3
Requires-Dist: tqdm
Requires-Dist: websocket-client
Requires-Dist: pycryptodome
Requires-Dist: mutagen
Requires-Dist: filetype
Dynamic: author
Dynamic: author-email
Dynamic: classifier
Dynamic: description
Dynamic: description-content-type
Dynamic: home-page
Dynamic: keywords
Dynamic: requires-dist
Dynamic: requires-python
Dynamic: summary
